hello_word_joao_neto/__init__.py
hello_word_joao_neto-0.1.dist-info/METADATA
hello_word_joao_neto-0.1.dist-info/WHEEL
hello_word_joao_neto-0.1.dist-info/top_level.txt
hello_word_joao_neto-0.1.dist-info/RECORD
