Metadata-Version: 2.1
Name: hello-word-joao-neto
Version: 0.1
Summary: Hello world joao neto
Home-page: https://gitlab.com/joaoNeto/alexandria
Author: Linode
Author-email: joao.neto@madeiramadeira.com.br
License: UNKNOWN
Platform: UNKNOWN
